page_objects/__init__.py
page_objects-1.0.1.dist-info/DESCRIPTION.rst
page_objects-1.0.1.dist-info/METADATA
page_objects-1.0.1.dist-info/metadata.json
page_objects-1.0.1.dist-info/RECORD
page_objects-1.0.1.dist-info/top_level.txt
page_objects-1.0.1.dist-info/WHEEL
page_objects-1.0.1.dist-info/zip-safe
